{
    "ability": {
        "citizen.job.medic": "tag.ability.selfheal",
        "citizen.job.scholar": "tag.ability.inspiration",
        "citizen.job.worker": "tag.ability.endurance",
        "citizen.job.technician": "tag.ability.expertise",
        "citizen.job.researcher": "tag.ability.curiosity",
        "citizen.job.artist": "tag.ability.creativity",
        "citizen.job.athlete": "tag.ability.strength",
        "citizen.job.foodie": "tag.ability.gluttonous"
    },
    "trade": [
        "tag.trade.merchant",
        "tag.trade.honest",
        "tag.trade.deceiver",
        "tag.trade.quality",
        "tag.trade.bargainer",
        "tag.trade.affordable",
        "tag.trade.greedy"
    ],
    "social": [
        "tag.social.chivalrous",
        "tag.social.fake",
        "tag.social.hospitable",
        "tag.social.cold",
        "tag.social.diplomatic",
        "tag.social.solitary",
        "tag.social.straightforward",
        "tag.social.mighty"
    ]
}